wagtailsimplemathcaptcha
