Metadata-Version: 1.1
Name: wagtail-simple-math-captcha
Version: 0.1.2
Summary: A simple math captcha field for Wagtail Form Pages based on Django Simple Math Captcha.
Home-page: https://bitbucket.org/jordanmarkov/wagtail-simple-math-captcha
Author: Jordan Markov
Author-email: jmarkov@gmail.com
License: BSD License
Download-URL: https://bitbucket.org/jordanmarkov/wagtail-simple-math-captcha/get/0.1.2.tar.gz
Platform: UNKNOWN
Classifier: Environment :: Web Environment
Classifier: Framework :: Django
Classifier: Intended Audience :: Developers
Classifier: License :: OSI Approved :: BSD License
Classifier: Operating System :: OS Independent
Classifier: Programming Language :: Python
Classifier: Topic :: Internet :: WWW/HTTP
Classifier: Topic :: Internet :: WWW/HTTP :: Dynamic Content
